.travis.yml
LICENSE
MANIFEST.in
README.rst
setup.cfg
setup.py
tox.ini
Mopidy_Tachikoma.egg-info/PKG-INFO
Mopidy_Tachikoma.egg-info/SOURCES.txt
Mopidy_Tachikoma.egg-info/dependency_links.txt
Mopidy_Tachikoma.egg-info/entry_points.txt
Mopidy_Tachikoma.egg-info/not-zip-safe
Mopidy_Tachikoma.egg-info/requires.txt
Mopidy_Tachikoma.egg-info/top_level.txt
mopidy_tachikoma/__init__.py
mopidy_tachikoma/bot.py
mopidy_tachikoma/ext.conf
tests/__init__.py
tests/test_extension.py
tests/test_helpers.py