Metadata-Version: 1.1
Name: Mopidy-Tachikoma
Version: 0.2.4
Summary: Mopidy extension for talking to Slack
Home-page: https://github.com/palfrey/mopidy-tachikoma
Author: Tom Parker
Author-email: palfrey@tevp.net
License: GNU Affero General Public License, Version 3
Platform: UNKNOWN
Classifier: Environment :: No Input/Output (Daemon)
Classifier: Intended Audience :: End Users/Desktop
Classifier: License :: OSI Approved :: GNU Affero General Public License v3
Classifier: Operating System :: OS Independent
Classifier: Programming Language :: Python :: 2
Classifier: Topic :: Multimedia :: Sound/Audio :: Players
